simplifiedapp/__init__.py
simplifiedapp/__main__.py
simplifiedapp/introspection_patched.py
simplifiedapp-0.7.3.dist-info/LICENSE
simplifiedapp-0.7.3.dist-info/METADATA
simplifiedapp-0.7.3.dist-info/WHEEL
simplifiedapp-0.7.3.dist-info/top_level.txt
simplifiedapp-0.7.3.dist-info/RECORD
